directline_client/__init__.py
directline_client/core.py
directline_client-0.2.2.dist-info/licenses/LICENSE
directline_client-0.2.2.dist-info/METADATA
directline_client-0.2.2.dist-info/WHEEL
directline_client-0.2.2.dist-info/top_level.txt
directline_client-0.2.2.dist-info/RECORD
