Metadata-Version: 2.4
Name: directline_client
Version: 0.2.2
Summary: A Python library intended to facilitate the use of Copilot Studio agents through code.
Author-email: Abel Soto Valdez <abelsotovaldez@gmail.com>
License: MIT
Project-URL: Homepage, https://github.com/Niels-Bored/Directline-Client
Requires-Python: >=3.8
License-File: LICENSE
Requires-Dist: requests==2.32.5
Dynamic: license-file
